{
  "version": 2,
  "projects": {
    "common": "libs/common",
    "components": "libs/components",
    "demo": "apps/demo",
    "demo-e2e": "apps/demo-e2e",
    "elements": "libs/elements",
    "executors": "libs/executors",
    "next-demo": "apps/next-demo",
    "next-demo-e2e": "apps/next-demo-e2e",
    "schematics": "libs/schematics",
    "schematics-x": "libs/schematics-x",
    "storybook": "libs/storybook",
    "web-api": "libs/web-api"
  },
  "$schema": "./node_modules/nx/schemas/workspace-schema.json"
}
